cinch/__init__.py
cinch/site.yml
cinch/teardown.yml
cinch/bin/__init__.py
cinch/bin/entry_point.py
cinch/bin/wrappers.py
cinch/files/jenkins-plugin-lists/README
cinch/files/jenkins-plugin-lists/default-test.txt
cinch/files/jenkins-plugin-lists/default.txt
cinch/files/jenkins-plugin-lists/optional-test.txt
cinch/files/jenkins-plugin-lists/optional.txt
cinch/group_vars/all
cinch/group_vars/cent6
cinch/group_vars/cent7
cinch/group_vars/fedora
cinch/group_vars/jenkins_docker_slave
cinch/group_vars/jenkins_master
cinch/group_vars/jenkins_slave
cinch/group_vars/rhel6
cinch/group_vars/rhel7
cinch/group_vars/rhel8
cinch/library/jenkins_cli_user.py
cinch/library/jenkins_script.py
cinch/library/jenkins_update_center.py
cinch/library/jenkins_user_api.py
cinch/library/line_match.py
cinch/roles/beaker-client/defaults/main.yml
cinch/roles/beaker-client/tasks/main.yml
cinch/roles/beaker-client/templates/etc/beaker/client.conf
cinch/roles/certificate_authority/defaults/main.yml
cinch/roles/certificate_authority/handlers/main.yml
cinch/roles/certificate_authority/tasks/main.yml
cinch/roles/check_ssh/defaults/main.yml
cinch/roles/check_ssh/tasks/main.yml
cinch/roles/dockerize/defaults/main.yml
cinch/roles/dockerize/tasks/main.yml
cinch/roles/jenkins_common/defaults/main.yml
cinch/roles/jenkins_common/handlers/main.yml
cinch/roles/jenkins_common/tasks/main.yml
cinch/roles/jenkins_common/vars/main.yml
cinch/roles/jenkins_docker_slave/defaults/main.yml
cinch/roles/jenkins_docker_slave/tasks/main.yml
cinch/roles/jenkins_master/defaults/main.yml
cinch/roles/jenkins_master/files/mass_disable.groovy
cinch/roles/jenkins_master/files/set_env.groovy
cinch/roles/jenkins_master/handlers/main.yml
cinch/roles/jenkins_master/tasks/configure.yml
cinch/roles/jenkins_master/tasks/ensure_up.yml
cinch/roles/jenkins_master/tasks/firewalld.yml
cinch/roles/jenkins_master/tasks/install.yml
cinch/roles/jenkins_master/tasks/main.yml
cinch/roles/jenkins_master/tasks/pin_plugin.yml
cinch-1.4.0.dist-info/LICENSE
cinch-1.4.0.dist-info/METADATA
cinch-1.4.0.dist-info/WHEEL
cinch-1.4.0.dist-info/entry_points.txt
cinch-1.4.0.dist-info/top_level.txt
cinch-1.4.0.dist-info/RECORD
