Metadata-Version: 2.1
Name: cinch
Version: 1.4.0
Summary: Cinch continuous integration setup
Home-page: https://github.com/RedHatQE/cinch
Author: RedHatQE
License: GPLv3
Keywords: continuous integration,ci,jenkins
Platform: UNKNOWN
Classifier: Development Status :: 5 - Production/Stable
Classifier: Intended Audience :: Developers
Classifier: Intended Audience :: Information Technology
Classifier: Topic :: Software Development :: Quality Assurance
Classifier: Topic :: Software Development :: Testing
Classifier: Topic :: Software Development :: Build Tools
Classifier: License :: OSI Approved :: GNU General Public License v3 (GPLv3)
Classifier: Programming Language :: Python :: 2.7
Classifier: Programming Language :: Python :: 3
Requires-Dist: ansible (>=2.4)
Requires-Dist: plumbum (>=1.6.0)
Provides-Extra: docs
Requires-Dist: sphinx-rtd-theme ; extra == 'docs'
Requires-Dist: sphinx ; extra == 'docs'
